algoliasearch_django/__init__.py
algoliasearch_django/apps.py
algoliasearch_django/decorators.py
algoliasearch_django/registration.py
algoliasearch_django/settings.py
algoliasearch_django/version.py
algoliasearch_django/management/__init__.py
algoliasearch_django/management/commands/__init__.py
algoliasearch_django/management/commands/algolia_applysettings.py
algoliasearch_django/management/commands/algolia_clearindex.py
algoliasearch_django/management/commands/algolia_reindex.py
algoliasearch_django/models/__init__.py
algoliasearch_django/models/aggregator.py
algoliasearch_django/models/base.py
algoliasearch_django/models/index.py
brightnetwork_algoliasearch_django-3.0.0.dist-info/LICENSE
brightnetwork_algoliasearch_django-3.0.0.dist-info/METADATA
brightnetwork_algoliasearch_django-3.0.0.dist-info/WHEEL
brightnetwork_algoliasearch_django-3.0.0.dist-info/top_level.txt
brightnetwork_algoliasearch_django-3.0.0.dist-info/RECORD
